<?xml version="1.0" encoding="utf-8"?>
<SoundBanksInfo Platform="Windows" BasePlatform="Windows" SchemaVersion="16" SoundBankVersion="145">
	<RootPaths>
		<ProjectRoot>../..</ProjectRoot>
		<SourceFilesRoot>../../.cache/Windows</SourceFilesRoot>
		<SoundBanksRoot>.</SoundBanksRoot>
		<ExternalSourcesInputFile></ExternalSourcesInputFile>
		<ExternalSourcesOutputRoot>.</ExternalSourcesOutputRoot>
	</RootPaths>
	<DialogueEvents/>
	<SoundBanks>
		<SoundBank Id="534561221" Type="User" Language="SFX" Hash="{7FEF2882-E44A-B191-D8B0-9371E52C2EAA}">
			<ShortName>MainSoundbank</ShortName>
			<Path>MainSoundbank.bnk</Path>
			<Media>
				<File Id="569312001" Language="SFX" Streaming="false" Location="Memory">
					<ShortName>Lego yoda death sound.wav</ShortName>
					<CachePath>SFX/Lego yoda death sound_10C4C929.wem</CachePath>
				</File>
			</Media>
			<Events>
				<Event Id="4205244797" Name="Test_Yoda" DurationType="OneShot" DurationMin="1.2871875" DurationMax="1.2871875">
					<MediaRefs>
						<MediaRef Id="569312001"/>
					</MediaRefs>
				</Event>
			</Events>
		</SoundBank>
		<SoundBank Id="1355168291" Type="User" Language="SFX" Hash="{88E35D17-EAD4-E077-3A06-4AEE3C068468}">
			<ShortName>Init</ShortName>
			<Path>Init.bnk</Path>
			<Plugins>
				<AudioDevices>
					<Plugin Id="2317455096" Name="No_Output" LibName="No Output" LibId="11862023"/>
					<Plugin Id="3859886410" Name="System" LibName="System" LibId="11403271"/>
				</AudioDevices>
			</Plugins>
			<Busses>
				<Bus Id="85412153" Name="Ambience"/>
				<Bus Id="1551306167" Name="UI"/>
				<Bus Id="3688490227" Name="SFX in world"/>
				<Bus Id="3803692087" Name="Master Audio Bus"/>
				<Bus Id="3991942870" Name="Music"/>
			</Busses>
			<GameParameters>
				<GameParameter Id="42448320" Name="SFX_Vol"/>
				<GameParameter Id="640949982" Name="Speed"/>
				<GameParameter Id="2246609544" Name="Music_Vol"/>
				<GameParameter Id="4035164671" Name="Ambience_Vol"/>
			</GameParameters>
		</SoundBank>
	</SoundBanks>
	<FileHash>{41FE67FD-271D-FCCA-9BD9-C45601BFC3FB}</FileHash>
</SoundBanksInfo>
